forcast_federated_learning/__init__.py
forcast_federated_learning/data.py
forcast_federated_learning/datasets.py
forcast_federated_learning/encryption.py
forcast_federated_learning/forcast_federated_learning.py
forcast_federated_learning/models.py
forcast_federated_learning/optim.py
forcast_federated_learning/security.py
forcast_federated_learning/utils.py
ffl-0.3.4.dist-info/LICENSE
ffl-0.3.4.dist-info/METADATA
ffl-0.3.4.dist-info/WHEEL
ffl-0.3.4.dist-info/top_level.txt
ffl-0.3.4.dist-info/RECORD
